klsframe/__about__.py
klsframe/__init__.py
klsframe/cli/__init__.py
klsframe/cli/cli.py
klsframe/gui/__init__.py
klsframe/gui/app_example.json
klsframe/gui/gui.py
klsframe/gui/guiLayout.py
klsframe/protypes/__init__.py
klsframe/protypes/kdicts.py
klsframe/protypes/klists.py
klsframe/protypes/kstrings.py
klsframe/system/__init__.py
klsframe/system/system.py
klsframe/utilities/__init__.py
klsframe/utilities/dataframe.py
klsframe/utilities/serializer.py
klsframe/utilities/statistics.py
klsframe/utilities/utils.py
klsframe/workers/APIworker.py
klsframe/workers/__init__.py
klsframe/workers/autobot.py
klsframe/workers/desktopWorker.py
klsframe/workers/webWorker.py
klsframe-0.3.2.dist-info/METADATA
klsframe-0.3.2.dist-info/WHEEL
klsframe-0.3.2.dist-info/licenses/LICENSE.txt
klsframe-0.3.2.dist-info/RECORD
